emtechstack/__init__.py
emtechstack/cli.py
emtechstack/commands.py
emtechstack/post_install.py
emtechstack-0.0.99.dist-info/METADATA
emtechstack-0.0.99.dist-info/WHEEL
emtechstack-0.0.99.dist-info/entry_points.txt
emtechstack-0.0.99.dist-info/top_level.txt
emtechstack-0.0.99.dist-info/RECORD
