Metadata-Version: 2.1
Name: emtechstack
Version: 0.0.99
Classifier: Programming Language :: Python :: 3
Classifier: Programming Language :: Python :: 3.8
Classifier: Programming Language :: Python :: 3.9
Classifier: Programming Language :: Python :: 3.10
Classifier: Programming Language :: Python :: 3.11
Classifier: Programming Language :: Python :: 3.12
Classifier: License :: OSI Approved :: MIT License
Classifier: Operating System :: OS Independent
Requires-Python: >=3.8
Requires-Dist: click
Requires-Dist: black
Requires-Dist: PyYAML
Requires-Dist: requests
Requires-Dist: tabulate
Requires-Dist: termcolor
